terracotta_toolbelt/__init__.py
terracotta_toolbelt/cog_utils.py
terracotta_toolbelt/url_utils.py
terracotta_toolbelt/extensions/__init__.py
terracotta_toolbelt/extensions/point.py
terracotta_toolbelt-0.0.5.dist-info/LICENSE
terracotta_toolbelt-0.0.5.dist-info/METADATA
terracotta_toolbelt-0.0.5.dist-info/WHEEL
terracotta_toolbelt-0.0.5.dist-info/top_level.txt
terracotta_toolbelt-0.0.5.dist-info/RECORD
