Metadata-Version: 2.1
Name: terracotta-toolbelt
Version: 0.0.5
Summary: A small Terracotta tool collection
Home-page: https://github.com/thedirtyfew/terracotta-toolbelt
Author: Emil Haldrup Eriksen
Author-email: emil.h.eriksen@gmail.com
License: MIT
Platform: UNKNOWN
Requires-Python: >=3.6
Requires-Dist: terracotta
Requires-Dist: flask
Requires-Dist: rasterio
